fbotics/__init__.py
fbotics/_version.py
fbotics/client/__init__.py
fbotics/client/exceptions.py
fbotics/models/__init__.py
fbotics/models/attachment.py
fbotics/models/message.py
fbotics/models/quick_reply.py
fbotics/models/recipient.py
fbotics/models/request.py
fbotics/models/buttons/__init__.py
fbotics/models/payloads/__init__.py
fbotics/models/payloads/button_template.py
fbotics/models/payloads/element.py
fbotics/models/payloads/generic_template.py
fbotics/models/payloads/list_template.py
fbotics/models/payloads/receipt_template.py
fbotics/models/payloads/rich_media.py
fbotics/tests/__init__.py
fbotics/tests/conftest.py
fbotics/tests/client/__init__.py
fbotics/tests/client/test_retrieve_supported_tags.py
fbotics/tests/client/test_send_button_template.py
fbotics/tests/client/test_send_generic_template.py
fbotics/tests/client/test_send_list_template.py
fbotics/tests/client/test_send_quick_replies.py
fbotics/tests/client/test_send_receipt_template.py
fbotics/tests/client/test_send_rich_media.py
fbotics/tests/client/test_send_text.py
fbotics-0.1.0.dist-info/METADATA
fbotics-0.1.0.dist-info/RECORD
fbotics-0.1.0.dist-info/WHEEL
fbotics-0.1.0.dist-info/top_level.txt
