Metadata-Version: 2.1
Name: fbotics
Version: 0.1.0
Summary: Client for Facebook Send API
Home-page: https://github.com/pasmod/fbotics
Author: AiBotics
Author-email: developer@aibotics.de
License: MIT
Platform: UNKNOWN
Classifier: License :: OSI Approved :: MIT License
Classifier: Programming Language :: Python
Classifier: Programming Language :: Python :: 3
Classifier: Programming Language :: Python :: 3.6
Classifier: Programming Language :: Python :: Implementation :: CPython
Classifier: Programming Language :: Python :: Implementation :: PyPy
Requires-Python: >=3.6.0
Requires-Dist: schematics (==2.1.0)
